Metadata-Version: 1.0
Name: flysight-manager
Version: 0.0.0
Summary: Tool for managing flysight data
Home-page: https://github.com/richo/flysight-manager
Author: Richo Healey
Author-email: richo@psych0tik.net
License: MIT
Platform: UNKNOWN
